[
  {
    "word": "Brand Equity",
    "meaning": "",
    "pronunciation": "",
    "definition": "The commercial value that derives from consumer perception of the brand name of a particular product or service.",
    "example": "",
    "category": "Marketing/sales",
    "subCategory": "Marketing/sales"
  },
  {
    "word": "Churn",
    "meaning": "",
    "pronunciation": "",
    "definition": "The rate at which customers stop doing business with an entity.",
    "example": "",
    "category": "Marketing/sales",
    "subCategory": "Marketing/sales"
  },
  {
    "word": "Cold Call",
    "meaning": "",
    "pronunciation": "",
    "definition": "An unsolicited visit or phone call made by someone trying to sell goods or services.",
    "example": "",
    "category": "Marketing/sales",
    "subCategory": "Marketing/sales"
  },
  {
    "word": "CRM",
    "meaning": "",
    "pronunciation": "",
    "definition": "Customer Relationship Management; a technology for managing all your company's relationships and interactions with customers and potential customers.",
    "example": "",
    "category": "Marketing/sales",
    "subCategory": "Marketing/sales"
  },
  {
    "word": "Cross-sell",
    "meaning": "",
    "pronunciation": "",
    "definition": "Sell a different product or service to an existing customer.",
    "example": "",
    "category": "Marketing/sales",
    "subCategory": "Marketing/sales"
  },
  {
    "word": "Funnel",
    "meaning": "",
    "pronunciation": "",
    "definition": "The buying process that companies lead customers through when purchasing products.",
    "example": "",
    "category": "Marketing/sales",
    "subCategory": "Marketing/sales"
  },
  {
    "word": "Lead",
    "meaning": "",
    "pronunciation": "",
    "definition": "A person or company that has shown interest in a brand's products or services.",
    "example": "",
    "category": "Marketing/sales",
    "subCategory": "Marketing/sales"
  },
  {
    "word": "Omnichannel",
    "meaning": "",
    "pronunciation": "",
    "definition": "A cross-channel content strategy that organizations use to improve their user experience and drive better relationships.",
    "example": "",
    "category": "Marketing/sales",
    "subCategory": "Marketing/sales"
  },
  {
    "word": "Pipeline",
    "meaning": "",
    "pronunciation": "",
    "definition": "A visual representation of sales prospects and where they are in the purchasing process.",
    "example": "",
    "category": "Marketing/sales",
    "subCategory": "Marketing/sales"
  },
  {
    "word": "Positioning",
    "meaning": "",
    "pronunciation": "",
    "definition": "The process of establishing the image or identity of a brand or product so that consumers perceive it in a certain way.",
    "example": "",
    "category": "Marketing/sales",
    "subCategory": "Marketing/sales"
  },
  {
    "word": "Prospect",
    "meaning": "",
    "pronunciation": "",
    "definition": "A potential customer or client who has been qualified as fitting certain criteria.",
    "example": "",
    "category": "Marketing/sales",
    "subCategory": "Marketing/sales"
  },
  {
    "word": "Quota",
    "meaning": "",
    "pronunciation": "",
    "definition": "A fixed share of something that a person or group is entitled to receive or is bound to contribute.",
    "example": "",
    "category": "Marketing/sales",
    "subCategory": "Marketing/sales"
  },
  {
    "word": "Segmentation",
    "meaning": "",
    "pronunciation": "",
    "definition": "The process of dividing a broad consumer or business market into sub-groups of consumers.",
    "example": "",
    "category": "Marketing/sales",
    "subCategory": "Marketing/sales"
  },
  {
    "word": "Targeting",
    "meaning": "",
    "pronunciation": "",
    "definition": "The process of evaluating each market segment's attractiveness and selecting one or more segments to enter.",
    "example": "",
    "category": "Marketing/sales",
    "subCategory": "Marketing/sales"
  },
  {
    "word": "Upsell",
    "meaning": "",
    "pronunciation": "",
    "definition": "Persuade a customer to buy a more expensive item or upgrade a product or service to make a more profitable sale.",
    "example": "",
    "category": "Marketing/sales",
    "subCategory": "Marketing/sales"
  }
]