[{"word":"Premise","meaning":"A statement or idea that is accepted as true and used as the basis for a logical argument.","example":"The argument is based on the premise that everyone deserves equal rights.","category":"Premises \u0026 Propositions"},{"word":"Conclusion","meaning":"The final decision or opinion you reach after considering all the facts and reasoning.","example":"After reviewing all the evidence, we came to the conclusion that the plan would work.","category":"Premises \u0026 Propositions"},{"word":"Claim","meaning":"A statement saying that something is true, which others may agree or disagree with.","example":"His claim that he finished the work early turned out to be false.","category":"Premises \u0026 Propositions"},{"word":"Proposition","meaning":"An idea or opinion that is put forward for people to consider or discuss.","example":"The proposition that working fewer hours increases productivity is being tested.","category":"Premises \u0026 Propositions"},{"word":"Assumption","meaning":"Something that you accept as true or certain to happen, even if you have no proof.","example":"Her plan failed because it was based on the wrong assumption about the weather.","category":"Premises \u0026 Propositions"},{"word":"Inference","meaning":"A guess or opinion you form based on the information or evidence you have.","example":"From his quiet behavior, we made the inference that he was unhappy.","category":"Premises \u0026 Propositions"},{"word":"Hypothesis","meaning":"An idea that attempts to explain something, which has not yet been proven true.","example":"The scientists tested their hypothesis by running several experiments.","category":"Premises \u0026 Propositions"},{"word":"Assertion","meaning":"A strong, confident statement that something is true, often made without proof.","example":"She made the assertion that local taxes were too high, but she had no data to prove it.","category":"Premises \u0026 Propositions"},{"word":"Warrant","meaning":"A reason or explanation that connects your evidence to your main claim.","example":"If you claim it will rain, the dark clouds in the sky are your warrant.","category":"Premises \u0026 Propositions"},{"word":"Presumption","meaning":"Believing that something is true because it is very likely, though not 100% certain.","example":"Under the law, there is a presumption of innocence until a person is proven guilty.","category":"Premises \u0026 Propositions"},{"word":"Line Of Reasoning","meaning":"A set of connected ideas and arguments that lead to a logical conclusion.","example":"I found it difficult to follow his line of reasoning during the debate.","category":"Premises \u0026 Propositions"},{"word":"Train Of Thought","meaning":"A sequence of connected thoughts or ideas in a person\u0027s mind.","example":"The loud noise outside broke my train of thought, and I forgot what I was saying.","category":"Premises \u0026 Propositions"},{"word":"Rationale","meaning":"The fundamental reasons or logical basis behind a decision, belief, or action.","example":"The director explained the rationale behind the decision to close the office.","category":"Premises \u0026 Propositions"},{"word":"Thesis","meaning":"The main statement, claim, or argument of an essay or presentation.","example":"The thesis of her essay was that technology has made communication harder, not easier.","category":"Premises \u0026 Propositions"},{"word":"Synthesis","meaning":"Combining different ideas or pieces of information to create a new, single understanding.","example":"His book is a brilliant synthesis of history, science, and philosophy.","category":"Premises \u0026 Propositions"},{"word":"Antithesis","meaning":"The exact opposite of a particular idea or statement.","example":"Cruelty to animals is the absolute antithesis of kindness.","category":"Premises \u0026 Propositions"},{"word":"Underlying Assumption","meaning":"A basic belief that is not directly spoken but forms the foundation of an argument.","example":"The underlying assumption of the project is that internet access will remain cheap.","category":"Premises \u0026 Propositions"},{"word":"Hidden Premise","meaning":"An unstated fact or belief that is necessary for an argument\u0027s conclusion to be true.","example":"His argument that we should buy the car has a hidden premise that we can afford it.","category":"Premises \u0026 Propositions"},{"word":"Grounds","meaning":"The facts, reasons, or evidence that support a claim or decision.","example":"The police had reasonable grounds to believe that a crime had been committed.","category":"Premises \u0026 Propositions"},{"word":"Postulate","meaning":"To suggest or accept something as true so that it can be used to build an argument.","example":"Let us postulate that all humans want to be happy, and see where that leads.","category":"Premises \u0026 Propositions"}]
