[
  {
    "word": "Acne",
    "meaning": "A skin condition characterized by red pimples on the skin.",
    "pronunciation": "",
    "definition": "A skin condition characterized by red pimples on the skin.",
    "example": "",
    "category": "Health, Diseases & Symptoms",
    "subCategory": "Health, Diseases & Symptoms"
  },
  {
    "word": "Allergen",
    "meaning": "A substance that causes an allergic reaction, such as pollen, dust, or certain foods.",
    "pronunciation": "",
    "definition": "A substance that causes an allergic reaction, such as pollen, dust, or certain foods.",
    "example": "Shellfish is a common allergen that can cause severe rashes or breathing difficulties.",
    "category": "Health, Diseases & Symptoms",
    "subCategory": "Health, Diseases & Symptoms"
  },
  {
    "word": "Alzheimer's disease",
    "meaning": "Progressive mental deterioration that can occur in middle or old age.",
    "pronunciation": "",
    "definition": "Progressive mental deterioration that can occur in middle or old age.",
    "example": "",
    "category": "Health, Diseases & Symptoms",
    "subCategory": "Health, Diseases & Symptoms"
  },
  {
    "word": "Anaphylaxis",
    "meaning": "A severe, life-threatening allergic reaction that can affect breathing and require immediate treatment.",
    "pronunciation": "",
    "definition": "A severe, life-threatening allergic reaction that can affect breathing and require immediate treatment.",
    "example": "Because of her severe peanut allergy, she always carries an epinephrine auto-injector in case of anaphylaxis.",
    "category": "Health, Diseases & Symptoms",
    "subCategory": "Health, Diseases & Symptoms"
  },
  {
    "word": "Anemia",
    "meaning": "A condition marked by a deficiency of red blood cells or of hemoglobin in the blood.",
    "pronunciation": "",
    "definition": "A condition marked by a deficiency of red blood cells or of hemoglobin in the blood.",
    "example": "",
    "category": "Health, Diseases & Symptoms",
    "subCategory": "Health, Diseases & Symptoms"
  },
  {
    "word": "Appendicitis",
    "meaning": "A serious medical condition in which the appendix becomes inflamed and painful.",
    "pronunciation": "",
    "definition": "A serious medical condition in which the appendix becomes inflamed and painful.",
    "example": "",
    "category": "Health, Diseases & Symptoms",
    "subCategory": "Health, Diseases & Symptoms"
  },
  {
    "word": "Arthritis",
    "meaning": "Painful inflammation and stiffness of the joints.",
    "pronunciation": "",
    "definition": "Painful inflammation and stiffness of the joints.",
    "example": "",
    "category": "Health, Diseases & Symptoms",
    "subCategory": "Health, Diseases & Symptoms"
  },
  {
    "word": "Asthma",
    "meaning": "A respiratory condition marked by spasms in the bronchi of the lungs.",
    "pronunciation": "",
    "definition": "A respiratory condition marked by spasms in the bronchi of the lungs.",
    "example": "",
    "category": "Health, Diseases & Symptoms",
    "subCategory": "Health, Diseases & Symptoms"
  },
  {
    "word": "Asthma Attack",
    "meaning": "A sudden worsening of asthma symptoms, making it very difficult to breathe.",
    "pronunciation": "",
    "definition": "A sudden worsening of asthma symptoms, making it very difficult to breathe.",
    "example": "She used her rescue inhaler to calm down her asthma attack.",
    "category": "Health, Diseases & Symptoms",
    "subCategory": "Health, Diseases & Symptoms"
  },
  {
    "word": "Backache",
    "meaning": "Prolonged pain in one's back.",
    "pronunciation": "",
    "definition": "Prolonged pain in one's back.",
    "example": "",
    "category": "Health, Diseases & Symptoms",
    "subCategory": "Health, Diseases & Symptoms"
  },
  {
    "word": "Bleeding",
    "meaning": "The escape of blood from a ruptured blood vessel, especially when external.",
    "pronunciation": "",
    "definition": "The escape of blood from a ruptured blood vessel, especially when external.",
    "example": "",
    "category": "Health, Diseases & Symptoms",
    "subCategory": "Health, Diseases & Symptoms"
  },
  {
    "word": "Blindness",
    "meaning": "The state or condition of being unable to see because of injury, disease, or a congenital condition.",
    "pronunciation": "",
    "definition": "The state or condition of being unable to see because of injury, disease, or a congenital condition.",
    "example": "",
    "category": "Health, Diseases & Symptoms",
    "subCategory": "Health, Diseases & Symptoms"
  },
  {
    "word": "Blister",
    "meaning": "A small bubble on the skin filled with serum and caused by friction, burning, or other damage.",
    "pronunciation": "",
    "definition": "A small bubble on the skin filled with serum and caused by friction, burning, or other damage.",
    "example": "",
    "category": "Health, Diseases & Symptoms",
    "subCategory": "Health, Diseases & Symptoms"
  },
  {
    "word": "Bloating",
    "meaning": "A swollen state caused by retention of fluid or gas.",
    "pronunciation": "",
    "definition": "A swollen state caused by retention of fluid or gas.",
    "example": "",
    "category": "Health, Diseases & Symptoms",
    "subCategory": "Health, Diseases & Symptoms"
  },
  {
    "word": "Body ache",
    "meaning": "Pain felt over the entire body.",
    "pronunciation": "",
    "definition": "Pain felt over the entire body.",
    "example": "",
    "category": "Health, Diseases & Symptoms",
    "subCategory": "Health, Diseases & Symptoms"
  },
  {
    "word": "Bronchitis",
    "meaning": "Inflammation of the mucous membrane in the bronchial tubes.",
    "pronunciation": "",
    "definition": "Inflammation of the mucous membrane in the bronchial tubes.",
    "example": "",
    "category": "Health, Diseases & Symptoms",
    "subCategory": "Health, Diseases & Symptoms"
  },
  {
    "word": "Bruise",
    "meaning": "An injury appearing as an area of discolored skin on the body, caused by a blow or impact.",
    "pronunciation": "",
    "definition": "An injury appearing as an area of discolored skin on the body, caused by a blow or impact.",
    "example": "",
    "category": "Health, Diseases & Symptoms",
    "subCategory": "Health, Diseases & Symptoms"
  },
  {
    "word": "Burn",
    "meaning": "Damage to the skin or other tissues caused by heat, chemicals, electricity, or radiation.",
    "pronunciation": "",
    "definition": "An injury caused by exposure to heat or flame.",
    "example": "You should run cool tap water over a minor burn for at least ten minutes.",
    "category": "Health, Diseases & Symptoms",
    "subCategory": "Health, Diseases & Symptoms"
  },
  {
    "word": "Callus",
    "meaning": "A thickened and hardened part of the skin or soft tissue, especially in an area that has been subjected to friction.",
    "pronunciation": "",
    "definition": "A thickened and hardened part of the skin or soft tissue, especially in an area that has been subjected to friction.",
    "example": "",
    "category": "Health, Diseases & Symptoms",
    "subCategory": "Health, Diseases & Symptoms"
  },
  {
    "word": "Cancer",
    "meaning": "A disease caused by an uncontrolled division of abnormal cells in a part of the body.",
    "pronunciation": "",
    "definition": "A disease caused by an uncontrolled division of abnormal cells in a part of the body.",
    "example": "",
    "category": "Health, Diseases & Symptoms",
    "subCategory": "Health, Diseases & Symptoms"
  },
  {
    "word": "Cardiac Arrest",
    "meaning": "A sudden loss of heart function, breathing, and consciousness, requiring immediate CPR.",
    "pronunciation": "",
    "definition": "A sudden loss of heart function, breathing, and consciousness, requiring immediate CPR.",
    "example": "When the runner collapsed, bystanders quickly recognized it was a cardiac arrest and began chest compressions.",
    "category": "Health, Diseases & Symptoms",
    "subCategory": "Health, Diseases & Symptoms"
  },
  {
    "word": "Cataract",
    "meaning": "A medical condition in which the lens of the eye becomes progressively opaque.",
    "pronunciation": "",
    "definition": "A medical condition in which the lens of the eye becomes progressively opaque.",
    "example": "",
    "category": "Health, Diseases & Symptoms",
    "subCategory": "Health, Diseases & Symptoms"
  },
  {
    "word": "Chickenpox",
    "meaning": "An infectious disease causing a mild fever and a rash of itchy inflamed blisters.",
    "pronunciation": "",
    "definition": "An infectious disease causing a mild fever and a rash of itchy inflamed blisters.",
    "example": "",
    "category": "Health, Diseases & Symptoms",
    "subCategory": "Health, Diseases & Symptoms"
  },
  {
    "word": "Chills",
    "meaning": "A feeling of coldness occurring during a high fever.",
    "pronunciation": "",
    "definition": "A feeling of coldness occurring during a high fever.",
    "example": "",
    "category": "Health, Diseases & Symptoms",
    "subCategory": "Health, Diseases & Symptoms"
  },
  {
    "word": "Choking",
    "meaning": "Being unable to breathe because the airway is blocked by food or an object.",
    "pronunciation": "",
    "definition": "Being unable to breathe because the airway is blocked by food or an object.",
    "example": "The waiter performed the Heimlich maneuver on the choking guest to clear his throat.",
    "category": "Health, Diseases & Symptoms",
    "subCategory": "Health, Diseases & Symptoms"
  },
  {
    "word": "Cholera",
    "meaning": "An infectious and often fatal bacterial disease of the small intestine.",
    "pronunciation": "",
    "definition": "An infectious and often fatal bacterial disease of the small intestine.",
    "example": "",
    "category": "Health, Diseases & Symptoms",
    "subCategory": "Health, Diseases & Symptoms"
  },
  {
    "word": "Cirrhosis",
    "meaning": "A chronic disease of the liver marked by degeneration of cells, inflammation, and fibrous thickening of tissue.",
    "pronunciation": "",
    "definition": "A chronic disease of the liver marked by degeneration of cells, inflammation, and fibrous thickening of tissue.",
    "example": "",
    "category": "Health, Diseases & Symptoms",
    "subCategory": "Health, Diseases & Symptoms"
  },
  {
    "word": "Coma",
    "meaning": "A state of deep unconsciousness that lasts for a prolonged or indefinite period.",
    "pronunciation": "",
    "definition": "A state of deep unconsciousness that lasts for a prolonged or indefinite period.",
    "example": "",
    "category": "Health, Diseases & Symptoms",
    "subCategory": "Health, Diseases & Symptoms"
  },
  {
    "word": "Concussion",
    "meaning": "A temporary brain injury caused by a blow to the head or a violent shaking of the head.",
    "pronunciation": "",
    "definition": "Temporary unconsciousness caused by a blow to the head.",
    "example": "The football player was taken off the field to be checked for a concussion after a hard tackle.",
    "category": "Health, Diseases & Symptoms",
    "subCategory": "Health, Diseases & Symptoms"
  },
  {
    "word": "Constipation",
    "meaning": "A condition in which there is difficulty in emptying the bowels.",
    "pronunciation": "",
    "definition": "A condition in which there is difficulty in emptying the bowels.",
    "example": "",
    "category": "Health, Diseases & Symptoms",
    "subCategory": "Health, Diseases & Symptoms"
  },
  {
    "word": "Convulsion",
    "meaning": "A sudden, violent, irregular movement of a limb or of the body.",
    "pronunciation": "",
    "definition": "A sudden, violent, irregular movement of a limb or of the body.",
    "example": "",
    "category": "Health, Diseases & Symptoms",
    "subCategory": "Health, Diseases & Symptoms"
  },
  {
    "word": "Cough",
    "meaning": "खांसी / खांसना",
    "pronunciation": "/k?f/",
    "definition": "To force air out of your lungs with a sudden sharp sound, or the act of doing this.",
    "example": "",
    "category": "Health, Diseases & Symptoms",
    "subCategory": "Health, Diseases & Symptoms"
  },
  {
    "word": "COVID-19",
    "meaning": "An acute respiratory illness in humans caused by a coronavirus.",
    "pronunciation": "",
    "definition": "An acute respiratory illness in humans caused by a coronavirus.",
    "example": "",
    "category": "Health, Diseases & Symptoms",
    "subCategory": "Health, Diseases & Symptoms"
  },
  {
    "word": "CPR",
    "meaning": "Abbreviation for Cardiopulmonary Resuscitation; an emergency procedure combining chest compressions and artificial ventilation.",
    "pronunciation": "",
    "definition": "Abbreviation for Cardiopulmonary Resuscitation; an emergency procedure combining chest compressions and artificial ventilation.",
    "example": "Learning how to perform CPR can help you save someone's life during a heart emergency.",
    "category": "Health, Diseases & Symptoms",
    "subCategory": "Health, Diseases & Symptoms"
  },
  {
    "word": "Cramp",
    "meaning": "A painful, involuntary contraction of a muscle or muscles.",
    "pronunciation": "",
    "definition": "A painful, involuntary contraction of a muscle or muscles.",
    "example": "",
    "category": "Health, Diseases & Symptoms",
    "subCategory": "Health, Diseases & Symptoms"
  },
  {
    "word": "Cut",
    "meaning": "?????",
    "pronunciation": "",
    "definition": "",
    "example": "",
    "category": "Health, Diseases & Symptoms",
    "subCategory": "Health, Diseases & Symptoms"
  },
  {
    "word": "Cyanosis",
    "meaning": "A bluish discoloration of the skin resulting from poor circulation or inadequate oxygenation of the blood.",
    "pronunciation": "",
    "definition": "A bluish discoloration of the skin resulting from poor circulation or inadequate oxygenation of the blood.",
    "example": "",
    "category": "Health, Diseases & Symptoms",
    "subCategory": "Health, Diseases & Symptoms"
  },
  {
    "word": "Deafness",
    "meaning": "The condition of lacking the power of hearing or having impaired hearing.",
    "pronunciation": "",
    "definition": "The condition of lacking the power of hearing or having impaired hearing.",
    "example": "",
    "category": "Health, Diseases & Symptoms",
    "subCategory": "Health, Diseases & Symptoms"
  },
  {
    "word": "Defibrillator",
    "meaning": "A device that gives a high-energy electric shock to the heart of someone in cardiac arrest to restore a normal rhythm.",
    "pronunciation": "",
    "definition": "A device that gives a high-energy electric shock to the heart of someone in cardiac arrest to restore a normal rhythm.",
    "example": "The airport has a public automated external defibrillator on the wall near the entrance.",
    "category": "Health, Diseases & Symptoms",
    "subCategory": "Health, Diseases & Symptoms"
  },
  {
    "word": "Delirium",
    "meaning": "An acutely disturbed state of mind that occurs in fever, intoxication, and other disorders.",
    "pronunciation": "",
    "definition": "An acutely disturbed state of mind that occurs in fever, intoxication, and other disorders.",
    "example": "",
    "category": "Health, Diseases & Symptoms",
    "subCategory": "Health, Diseases & Symptoms"
  },
  {
    "word": "Dengue",
    "meaning": "A debilitating viral disease of the tropics, transmitted by mosquitoes.",
    "pronunciation": "",
    "definition": "A debilitating viral disease of the tropics, transmitted by mosquitoes.",
    "example": "",
    "category": "Health, Diseases & Symptoms",
    "subCategory": "Health, Diseases & Symptoms"
  },
  {
    "word": "Diabetes",
    "meaning": "A disease in which the body's ability to produce or respond to the hormone insulin is impaired.",
    "pronunciation": "",
    "definition": "A disease in which the body's ability to produce or respond to the hormone insulin is impaired.",
    "example": "",
    "category": "Health, Diseases & Symptoms",
    "subCategory": "Health, Diseases & Symptoms"
  },
  {
    "word": "Diarrhea",
    "meaning": "A condition in which feces are discharged from the bowels frequently and in a liquid form.",
    "pronunciation": "",
    "definition": "A condition in which feces are discharged from the bowels frequently and in a liquid form.",
    "example": "",
    "category": "Health, Diseases & Symptoms",
    "subCategory": "Health, Diseases & Symptoms"
  },
  {
    "word": "Diphtheria",
    "meaning": "An acute, highly contagious bacterial disease causing inflammation of the mucous membranes.",
    "pronunciation": "",
    "definition": "An acute, highly contagious bacterial disease causing inflammation of the mucous membranes.",
    "example": "",
    "category": "Health, Diseases & Symptoms",
    "subCategory": "Health, Diseases & Symptoms"
  },
  {
    "word": "Dislocation",
    "meaning": "An injury where a joint is forced out of its normal position.",
    "pronunciation": "",
    "definition": "Injury or disability caused when the normal position of a joint or other part of the body is disturbed.",
    "example": "Falling off his bicycle resulted in a painful shoulder dislocation.",
    "category": "Health, Diseases & Symptoms",
    "subCategory": "Health, Diseases & Symptoms"
  },
  {
    "word": "Dizziness",
    "meaning": "A sensation of spinning around and losing one's balance.",
    "pronunciation": "",
    "definition": "A sensation of spinning around and losing one's balance.",
    "example": "",
    "category": "Health, Diseases & Symptoms",
    "subCategory": "Health, Diseases & Symptoms"
  },
  {
    "word": "Dysentery",
    "meaning": "Infection of the intestines resulting in severe diarrhea with the presence of blood and mucus in the feces.",
    "pronunciation": "",
    "definition": "Infection of the intestines resulting in severe diarrhea with the presence of blood and mucus in the feces.",
    "example": "",
    "category": "Health, Diseases & Symptoms",
    "subCategory": "Health, Diseases & Symptoms"
  },
  {
    "word": "Earache",
    "meaning": "Pain inside the ear.",
    "pronunciation": "",
    "definition": "Pain inside the ear.",
    "example": "",
    "category": "Health, Diseases & Symptoms",
    "subCategory": "Health, Diseases & Symptoms"
  },
  {
    "word": "Eczema",
    "meaning": "A medical condition in which patches of skin become rough and inflamed.",
    "pronunciation": "",
    "definition": "A medical condition in which patches of skin become rough and inflamed.",
    "example": "",
    "category": "Health, Diseases & Symptoms",
    "subCategory": "Health, Diseases & Symptoms"
  },
  {
    "word": "Encephalitis",
    "meaning": "Inflammation of the brain, caused by infection or an allergic reaction.",
    "pronunciation": "",
    "definition": "Inflammation of the brain, caused by infection or an allergic reaction.",
    "example": "",
    "category": "Health, Diseases & Symptoms",
    "subCategory": "Health, Diseases & Symptoms"
  },
  {
    "word": "Epilepsy",
    "meaning": "A neurological disorder marked by sudden recurrent episodes of sensory disturbance.",
    "pronunciation": "",
    "definition": "A neurological disorder marked by sudden recurrent episodes of sensory disturbance.",
    "example": "",
    "category": "Health, Diseases & Symptoms",
    "subCategory": "Health, Diseases & Symptoms"
  },
  {
    "word": "Fatigue",
    "meaning": "Extreme tiredness resulting from mental or physical exertion or illness.",
    "pronunciation": "",
    "definition": "Extreme tiredness resulting from mental or physical exertion or illness.",
    "example": "",
    "category": "Health, Diseases & Symptoms",
    "subCategory": "Health, Diseases & Symptoms"
  },
  {
    "word": "Fever",
    "meaning": "बुखार",
    "pronunciation": "/?fi?v?r/",
    "definition": "An abnormally high body temperature, usually accompanied by shivering and headache.",
    "example": "",
    "category": "Health, Diseases & Symptoms",
    "subCategory": "Health, Diseases & Symptoms"
  },
  {
    "word": "First Aid",
    "meaning": "Emergency care or treatment given to an ill or injured person before regular medical aid can be obtained.",
    "pronunciation": "",
    "definition": "Emergency care or treatment given to an ill or injured person before regular medical aid can be obtained.",
    "example": "The school teacher applied first aid to the child's scraped knee.",
    "category": "Health, Diseases & Symptoms",
    "subCategory": "Health, Diseases & Symptoms"
  },
  {
    "word": "Flatulence",
    "meaning": "The accumulation of gas in the alimentary canal.",
    "pronunciation": "",
    "definition": "The accumulation of gas in the alimentary canal.",
    "example": "",
    "category": "Health, Diseases & Symptoms",
    "subCategory": "Health, Diseases & Symptoms"
  },
  {
    "word": "Flu",
    "meaning": "A highly contagious viral infection of the respiratory passages.",
    "pronunciation": "",
    "definition": "A highly contagious viral infection of the respiratory passages.",
    "example": "",
    "category": "Health, Diseases & Symptoms",
    "subCategory": "Health, Diseases & Symptoms"
  },
  {
    "word": "Fracture",
    "meaning": "A break or crack in a bone.",
    "pronunciation": "",
    "definition": "The cracking or breaking of a hard object or material, typically a bone.",
    "example": "The doctor took an X-ray to confirm if the boy had a fracture in his arm.",
    "category": "Health, Diseases & Symptoms",
    "subCategory": "Health, Diseases & Symptoms"
  },
  {
    "word": "Frostbite",
    "meaning": "Injury to body tissues caused by exposure to extreme cold.",
    "pronunciation": "",
    "definition": "Injury to body tissues caused by exposure to extreme cold.",
    "example": "",
    "category": "Health, Diseases & Symptoms",
    "subCategory": "Health, Diseases & Symptoms"
  },
  {
    "word": "Glaucoma",
    "meaning": "A condition of increased pressure within the eyeball, causing gradual loss of sight.",
    "pronunciation": "",
    "definition": "A condition of increased pressure within the eyeball, causing gradual loss of sight.",
    "example": "",
    "category": "Health, Diseases & Symptoms",
    "subCategory": "Health, Diseases & Symptoms"
  },
  {
    "word": "Goiter",
    "meaning": "A swelling of the neck resulting from enlargement of the thyroid gland.",
    "pronunciation": "",
    "definition": "A swelling of the neck resulting from enlargement of the thyroid gland.",
    "example": "",
    "category": "Health, Diseases & Symptoms",
    "subCategory": "Health, Diseases & Symptoms"
  },
  {
    "word": "Gonorrhea",
    "meaning": "A venereal disease involving inflammatory discharge from the urethra or vagina.",
    "pronunciation": "",
    "definition": "A venereal disease involving inflammatory discharge from the urethra or vagina.",
    "example": "",
    "category": "Health, Diseases & Symptoms",
    "subCategory": "Health, Diseases & Symptoms"
  },
  {
    "word": "Gout",
    "meaning": "A disease in which defective metabolism of uric acid causes arthritis.",
    "pronunciation": "",
    "definition": "A disease in which defective metabolism of uric acid causes arthritis.",
    "example": "",
    "category": "Health, Diseases & Symptoms",
    "subCategory": "Health, Diseases & Symptoms"
  },
  {
    "word": "Graze",
    "meaning": "A superficial injury caused by rubbing against a rough surface.",
    "pronunciation": "",
    "definition": "A superficial injury caused by rubbing against a rough surface.",
    "example": "",
    "category": "Health, Diseases & Symptoms",
    "subCategory": "Health, Diseases & Symptoms"
  },
  {
    "word": "Headache",
    "meaning": "A continuous pain in the head.",
    "pronunciation": "",
    "definition": "",
    "example": "",
    "category": "Health, Diseases & Symptoms",
    "subCategory": "Health, Diseases & Symptoms"
  },
  {
    "word": "Heart attack",
    "meaning": "A sudden and sometimes fatal occurrence of coronary thrombosis.",
    "pronunciation": "",
    "definition": "A sudden and sometimes fatal occurrence of coronary thrombosis.",
    "example": "",
    "category": "Health, Diseases & Symptoms",
    "subCategory": "Health, Diseases & Symptoms"
  },
  {
    "word": "Heartburn",
    "meaning": "A form of indigestion felt as a burning sensation in the chest.",
    "pronunciation": "",
    "definition": "A form of indigestion felt as a burning sensation in the chest.",
    "example": "",
    "category": "Health, Diseases & Symptoms",
    "subCategory": "Health, Diseases & Symptoms"
  },
  {
    "word": "Heatstroke",
    "meaning": "A life-threatening condition caused by the body overheating, usually from prolonged physical activity in high temperatures.",
    "pronunciation": "",
    "definition": "A life-threatening condition caused by the body overheating, usually from prolonged physical activity in high temperatures.",
    "example": "Drinking plenty of water can help prevent heatstroke on a hot day.",
    "category": "Health, Diseases & Symptoms",
    "subCategory": "Health, Diseases & Symptoms"
  },
  {
    "word": "Hemorrhage",
    "meaning": "Severe or uncontrolled bleeding from a ruptured blood vessel.",
    "pronunciation": "",
    "definition": "An escape of blood from a ruptured blood vessel, especially when internal.",
    "example": "The paramedic applied pressure to the wound to stop the hemorrhage.",
    "category": "Health, Diseases & Symptoms",
    "subCategory": "Health, Diseases & Symptoms"
  },
  {
    "word": "Hepatitis",
    "meaning": "A disease characterized by inflammation of the liver.",
    "pronunciation": "",
    "definition": "A disease characterized by inflammation of the liver.",
    "example": "",
    "category": "Health, Diseases & Symptoms",
    "subCategory": "Health, Diseases & Symptoms"
  },
  {
    "word": "Hernia",
    "meaning": "A condition in which part of an organ is displaced and protrudes through the wall of the cavity containing it.",
    "pronunciation": "",
    "definition": "A condition in which part of an organ is displaced and protrudes through the wall of the cavity containing it.",
    "example": "",
    "category": "Health, Diseases & Symptoms",
    "subCategory": "Health, Diseases & Symptoms"
  },
  {
    "word": "Hiccup",
    "meaning": "An involuntary spasm of the diaphragm and respiratory organs.",
    "pronunciation": "",
    "definition": "An involuntary spasm of the diaphragm and respiratory organs.",
    "example": "",
    "category": "Health, Diseases & Symptoms",
    "subCategory": "Health, Diseases & Symptoms"
  },
  {
    "word": "HIV/AIDS",
    "meaning": "A chronic, potentially life-threatening condition caused by the human immunodeficiency virus.",
    "pronunciation": "",
    "definition": "A chronic, potentially life-threatening condition caused by the human immunodeficiency virus.",
    "example": "",
    "category": "Health, Diseases & Symptoms",
    "subCategory": "Health, Diseases & Symptoms"
  },
  {
    "word": "Hives",
    "meaning": "A rash of round, red welts on the skin that itch intensely.",
    "pronunciation": "",
    "definition": "A rash of round, red welts on the skin that itch intensely.",
    "example": "",
    "category": "Health, Diseases & Symptoms",
    "subCategory": "Health, Diseases & Symptoms"
  },
  {
    "word": "Hypertension",
    "meaning": "Abnormally high blood pressure.",
    "pronunciation": "",
    "definition": "Abnormally high blood pressure.",
    "example": "",
    "category": "Health, Diseases & Symptoms",
    "subCategory": "Health, Diseases & Symptoms"
  },
  {
    "word": "Hyperventilation",
    "meaning": "Breathing too fast and deep, often caused by panic or anxiety, leading to dizziness.",
    "pronunciation": "",
    "definition": "Breathing too fast and deep, often caused by panic or anxiety, leading to dizziness.",
    "example": "Sitting down and breathing slowly helped her recover from hyperventilation.",
    "category": "Health, Diseases & Symptoms",
    "subCategory": "Health, Diseases & Symptoms"
  },
  {
    "word": "Hypotension",
    "meaning": "Abnormally low blood pressure.",
    "pronunciation": "",
    "definition": "Abnormally low blood pressure.",
    "example": "",
    "category": "Health, Diseases & Symptoms",
    "subCategory": "Health, Diseases & Symptoms"
  },
  {
    "word": "Hypothermia",
    "meaning": "A dangerous drop in body temperature, usually caused by prolonged exposure to cold.",
    "pronunciation": "",
    "definition": "A dangerous drop in body temperature, usually caused by prolonged exposure to cold.",
    "example": "The hikers developed hypothermia after getting wet in the freezing rain.",
    "category": "Health, Diseases & Symptoms",
    "subCategory": "Health, Diseases & Symptoms"
  },
  {
    "word": "Hypoventilation",
    "meaning": "Breathing that is too shallow or too slow, which does not provide enough oxygen to the body.",
    "pronunciation": "",
    "definition": "Breathing that is too shallow or too slow, which does not provide enough oxygen to the body.",
    "example": "The patient showed signs of hypoventilation after receiving heavy pain medication.",
    "category": "Health, Diseases & Symptoms",
    "subCategory": "Health, Diseases & Symptoms"
  },
  {
    "word": "Indigestion",
    "meaning": "Pain or discomfort in the stomach associated with difficulty in digesting food.",
    "pronunciation": "",
    "definition": "Pain or discomfort in the stomach associated with difficulty in digesting food.",
    "example": "",
    "category": "Health, Diseases & Symptoms",
    "subCategory": "Health, Diseases & Symptoms"
  },
  {
    "word": "Insomnia",
    "meaning": "Habitual sleeplessness; inability to sleep.",
    "pronunciation": "",
    "definition": "Habitual sleeplessness; inability to sleep.",
    "example": "",
    "category": "Health, Diseases & Symptoms",
    "subCategory": "Health, Diseases & Symptoms"
  },
  {
    "word": "Intubate",
    "meaning": "To insert a tube into a patient's trachea (windpipe) to help them breathe.",
    "pronunciation": "",
    "definition": "To insert a tube into a patient's trachea (windpipe) to help them breathe.",
    "example": "The doctor had to intubate the patient because they could not breathe on their own.",
    "category": "Health, Diseases & Symptoms",
    "subCategory": "Health, Diseases & Symptoms"
  },
  {
    "word": "Itching",
    "meaning": "Have or cause an uncomfortable sensation on the skin that makes one want to scratch.",
    "pronunciation": "",
    "definition": "Have or cause an uncomfortable sensation on the skin that makes one want to scratch.",
    "example": "",
    "category": "Health, Diseases & Symptoms",
    "subCategory": "Health, Diseases & Symptoms"
  },
  {
    "word": "Jaundice",
    "meaning": "A medical condition with yellowing of the skin or whites of the eyes.",
    "pronunciation": "",
    "definition": "A medical condition with yellowing of the skin or whites of the eyes.",
    "example": "",
    "category": "Health, Diseases & Symptoms",
    "subCategory": "Health, Diseases & Symptoms"
  },
  {
    "word": "Kidney failure",
    "meaning": "A medical condition in which the kidneys fail to adequately filter waste products from the blood.",
    "pronunciation": "",
    "definition": "A medical condition in which the kidneys fail to adequately filter waste products from the blood.",
    "example": "",
    "category": "Health, Diseases & Symptoms",
    "subCategory": "Health, Diseases & Symptoms"
  },
  {
    "word": "Laceration",
    "meaning": "A deep cut or tear in skin or flesh.",
    "pronunciation": "",
    "definition": "A deep cut or tear in skin or flesh.",
    "example": "He needed six stitches to close the laceration on his forehead.",
    "category": "Health, Diseases & Symptoms",
    "subCategory": "Health, Diseases & Symptoms"
  },
  {
    "word": "Leprosy",
    "meaning": "A contagious disease that affects the skin, mucous membranes, and nerves, causing discoloration and lumps on the skin.",
    "pronunciation": "",
    "definition": "A contagious disease that affects the skin, mucous membranes, and nerves, causing discoloration and lumps on the skin.",
    "example": "",
    "category": "Health, Diseases & Symptoms",
    "subCategory": "Health, Diseases & Symptoms"
  },
  {
    "word": "Leukemia",
    "meaning": "A malignant progressive disease in which the bone marrow produces increased numbers of immature or abnormal leukocytes.",
    "pronunciation": "",
    "definition": "A malignant progressive disease in which the bone marrow produces increased numbers of immature or abnormal leukocytes.",
    "example": "",
    "category": "Health, Diseases & Symptoms",
    "subCategory": "Health, Diseases & Symptoms"
  },
  {
    "word": "Malaria",
    "meaning": "An intermittent and remittent fever caused by a protozoan parasite.",
    "pronunciation": "",
    "definition": "An intermittent and remittent fever caused by a protozoan parasite.",
    "example": "",
    "category": "Health, Diseases & Symptoms",
    "subCategory": "Health, Diseases & Symptoms"
  },
  {
    "word": "Measles",
    "meaning": "An infectious viral disease causing fever and a red rash on the skin.",
    "pronunciation": "",
    "definition": "An infectious viral disease causing fever and a red rash on the skin.",
    "example": "",
    "category": "Health, Diseases & Symptoms",
    "subCategory": "Health, Diseases & Symptoms"
  },
  {
    "word": "Meningitis",
    "meaning": "Inflammation of the meninges caused by viral or bacterial infection.",
    "pronunciation": "",
    "definition": "Inflammation of the meninges caused by viral or bacterial infection.",
    "example": "",
    "category": "Health, Diseases & Symptoms",
    "subCategory": "Health, Diseases & Symptoms"
  },
  {
    "word": "Migraine",
    "meaning": "A recurrent throbbing headache that typically affects one side of the head.",
    "pronunciation": "",
    "definition": "A recurrent throbbing headache that typically affects one side of the head.",
    "example": "",
    "category": "Health, Diseases & Symptoms",
    "subCategory": "Health, Diseases & Symptoms"
  },
  {
    "word": "Mumps",
    "meaning": "A contagious and infectious viral disease causing swelling of the parotid salivary glands in the face.",
    "pronunciation": "",
    "definition": "A contagious and infectious viral disease causing swelling of the parotid salivary glands in the face.",
    "example": "",
    "category": "Health, Diseases & Symptoms",
    "subCategory": "Health, Diseases & Symptoms"
  },
  {
    "word": "Nasal congestion",
    "meaning": "The blockage of the nasal passages usually due to membranes lining the nose becoming swollen.",
    "pronunciation": "",
    "definition": "The blockage of the nasal passages usually due to membranes lining the nose becoming swollen.",
    "example": "",
    "category": "Health, Diseases & Symptoms",
    "subCategory": "Health, Diseases & Symptoms"
  },
  {
    "word": "Osteoporosis",
    "meaning": "A medical condition in which the bones become brittle and fragile.",
    "pronunciation": "",
    "definition": "A medical condition in which the bones become brittle and fragile.",
    "example": "",
    "category": "Health, Diseases & Symptoms",
    "subCategory": "Health, Diseases & Symptoms"
  },
  {
    "word": "Palpitation",
    "meaning": "A noticeably rapid, strong, or irregular heartbeat due to agitation, exertion, or illness.",
    "pronunciation": "",
    "definition": "A noticeably rapid, strong, or irregular heartbeat due to agitation, exertion, or illness.",
    "example": "",
    "category": "Health, Diseases & Symptoms",
    "subCategory": "Health, Diseases & Symptoms"
  },
  {
    "word": "Paralysis",
    "meaning": "The loss of the ability to move in part or most of the body.",
    "pronunciation": "",
    "definition": "The loss of the ability to move in part or most of the body.",
    "example": "",
    "category": "Health, Diseases & Symptoms",
    "subCategory": "Health, Diseases & Symptoms"
  },
  {
    "word": "Parkinson's disease",
    "meaning": "A progressive disease of the nervous system marked by tremor, muscular rigidity, and slow, imprecise movement.",
    "pronunciation": "",
    "definition": "A progressive disease of the nervous system marked by tremor, muscular rigidity, and slow, imprecise movement.",
    "example": "",
    "category": "Health, Diseases & Symptoms",
    "subCategory": "Health, Diseases & Symptoms"
  },
  {
    "word": "Phlegm",
    "meaning": "The thick viscous substance secreted by the mucous membranes of the respiratory passages.",
    "pronunciation": "",
    "definition": "The thick viscous substance secreted by the mucous membranes of the respiratory passages.",
    "example": "",
    "category": "Health, Diseases & Symptoms",
    "subCategory": "Health, Diseases & Symptoms"
  },
  {
    "word": "Pneumonia",
    "meaning": "Lung inflammation caused by bacterial or viral infection.",
    "pronunciation": "",
    "definition": "Lung inflammation caused by bacterial or viral infection.",
    "example": "",
    "category": "Health, Diseases & Symptoms",
    "subCategory": "Health, Diseases & Symptoms"
  },
  {
    "word": "Polio",
    "meaning": "An infectious viral disease that affects the central nervous system and can cause temporary or permanent paralysis.",
    "pronunciation": "",
    "definition": "An infectious viral disease that affects the central nervous system and can cause temporary or permanent paralysis.",
    "example": "",
    "category": "Health, Diseases & Symptoms",
    "subCategory": "Health, Diseases & Symptoms"
  },
  {
    "word": "Pulse",
    "meaning": "The regular beating of the heart, which can be felt in the wrist or neck.",
    "pronunciation": "",
    "definition": "The regular beating of the heart, which can be felt in the wrist or neck.",
    "example": "The nurse checked the patient's pulse to make sure it was steady.",
    "category": "Health, Diseases & Symptoms",
    "subCategory": "Health, Diseases & Symptoms"
  },
  {
    "word": "Rabies",
    "meaning": "A contagious and fatal viral disease of dogs and other mammals that causes madness and convulsions.",
    "pronunciation": "",
    "definition": "A contagious and fatal viral disease of dogs and other mammals that causes madness and convulsions.",
    "example": "",
    "category": "Health, Diseases & Symptoms",
    "subCategory": "Health, Diseases & Symptoms"
  },
  {
    "word": "Rash",
    "meaning": "An area of reddening of a person's skin, sometimes with raised spots.",
    "pronunciation": "",
    "definition": "An area of reddening of a person's skin, sometimes with raised spots.",
    "example": "",
    "category": "Health, Diseases & Symptoms",
    "subCategory": "Health, Diseases & Symptoms"
  },
  {
    "word": "Resuscitate",
    "meaning": "To revive someone from unconsciousness or apparent death.",
    "pronunciation": "",
    "definition": "To revive someone from unconsciousness or apparent death.",
    "example": "The lifeguards managed to resuscitate the boy who had nearly drowned.",
    "category": "Health, Diseases & Symptoms",
    "subCategory": "Health, Diseases & Symptoms"
  },
  {
    "word": "Rheumatism",
    "meaning": "Any disease marked by inflammation and pain in the joints, muscles, or fibrous tissue.",
    "pronunciation": "",
    "definition": "Any disease marked by inflammation and pain in the joints, muscles, or fibrous tissue.",
    "example": "",
    "category": "Health, Diseases & Symptoms",
    "subCategory": "Health, Diseases & Symptoms"
  },
  {
    "word": "Runny nose",
    "meaning": "A condition in which excess fluid flows from the nostrils.",
    "pronunciation": "",
    "definition": "A condition in which excess fluid flows from the nostrils.",
    "example": "",
    "category": "Health, Diseases & Symptoms",
    "subCategory": "Health, Diseases & Symptoms"
  },
  {
    "word": "Scald",
    "meaning": "Injure with very hot liquid or steam.",
    "pronunciation": "",
    "definition": "Injure with very hot liquid or steam.",
    "example": "",
    "category": "Health, Diseases & Symptoms",
    "subCategory": "Health, Diseases & Symptoms"
  },
  {
    "word": "Scar",
    "meaning": "A mark left on the skin or within body tissue where a wound, burn, or sore has not healed completely.",
    "pronunciation": "",
    "definition": "A mark left on the skin or within body tissue where a wound, burn, or sore has not healed completely.",
    "example": "",
    "category": "Health, Diseases & Symptoms",
    "subCategory": "Health, Diseases & Symptoms"
  },
  {
    "word": "Scrape",
    "meaning": "To automatically extract large amounts of public data or text from websites using a computer program (strong alternative to 'copy text off website manually' or 'grab web text').",
    "pronunciation": "",
    "definition": "An injury or mark caused by scraping.",
    "example": "The tool will scrape product prices from competitor sites to compare them automatically.",
    "category": "Health, Diseases & Symptoms",
    "subCategory": "Software Development & Lifecycle"
  },
  {
    "word": "Scratch",
    "meaning": "A mark or wound made by scratching.",
    "pronunciation": "",
    "definition": "A mark or wound made by scratching.",
    "example": "",
    "category": "Health, Diseases & Symptoms",
    "subCategory": "Health, Diseases & Symptoms"
  },
  {
    "word": "Seizure",
    "meaning": "A sudden, uncontrolled electrical disturbance in the brain that can cause changes in behavior or movements.",
    "pronunciation": "",
    "definition": "A sudden attack of illness, especially a stroke or an epileptic fit.",
    "example": "During a seizure, you should clear the area of sharp objects and cushion the person's head.",
    "category": "Health, Diseases & Symptoms",
    "subCategory": "Health, Diseases & Symptoms"
  },
  {
    "word": "Sepsis",
    "meaning": "A life-threatening condition that arises when the body's response to infection causes injury to its own tissues and organs.",
    "pronunciation": "",
    "definition": "A life-threatening condition that arises when the body's response to infection causes injury to its own tissues and organs.",
    "example": "",
    "category": "Health, Diseases & Symptoms",
    "subCategory": "Health, Diseases & Symptoms"
  },
  {
    "word": "Shock",
    "meaning": "A life-threatening medical condition where the body does not get enough blood flow, making the person pale and weak.",
    "pronunciation": "",
    "definition": "A sudden feeling of disturbance or upset caused by something unexpected or disturbing",
    "example": "Keep the patient warm and lie them flat on their back to treat them for shock.",
    "category": "Health, Diseases & Symptoms",
    "subCategory": "Health, Diseases & Symptoms"
  },
  {
    "word": "Shortness of breath",
    "meaning": "Intense tightening in the chest, air hunger, difficulty breathing, breathlessness.",
    "pronunciation": "",
    "definition": "Intense tightening in the chest, air hunger, difficulty breathing, breathlessness.",
    "example": "",
    "category": "Health, Diseases & Symptoms",
    "subCategory": "Health, Diseases & Symptoms"
  },
  {
    "word": "Smallpox",
    "meaning": "An eradicated virus that used to be contagious, disfiguring, and often deadly.",
    "pronunciation": "",
    "definition": "An eradicated virus that used to be contagious, disfiguring, and often deadly.",
    "example": "",
    "category": "Health, Diseases & Symptoms",
    "subCategory": "Health, Diseases & Symptoms"
  },
  {
    "word": "Sneezing",
    "meaning": "Make a sudden involuntary expulsion of air from the nose and mouth due to irritation of one's nostrils.",
    "pronunciation": "",
    "definition": "Make a sudden involuntary expulsion of air from the nose and mouth due to irritation of one's nostrils.",
    "example": "",
    "category": "Health, Diseases & Symptoms",
    "subCategory": "Health, Diseases & Symptoms"
  },
  {
    "word": "Sore throat",
    "meaning": "A condition marked by pain in the throat, typically caused by inflammation.",
    "pronunciation": "",
    "definition": "A condition marked by pain in the throat, typically caused by inflammation.",
    "example": "",
    "category": "Health, Diseases & Symptoms",
    "subCategory": "Health, Diseases & Symptoms"
  },
  {
    "word": "Spasm",
    "meaning": "A sudden involuntary muscular contraction or convulsive movement.",
    "pronunciation": "",
    "definition": "A sudden involuntary muscular contraction or convulsive movement.",
    "example": "",
    "category": "Health, Diseases & Symptoms",
    "subCategory": "Health, Diseases & Symptoms"
  },
  {
    "word": "Splinter",
    "meaning": "A small, thin, sharp piece of wood, glass, or similar material broken off from a larger piece.",
    "pronunciation": "",
    "definition": "A small, thin, sharp piece of wood, glass, or similar material broken off from a larger piece.",
    "example": "",
    "category": "Health, Diseases & Symptoms",
    "subCategory": "Health, Diseases & Symptoms"
  },
  {
    "word": "Stomachache",
    "meaning": "A pain in a person's belly.",
    "pronunciation": "",
    "definition": "",
    "example": "",
    "category": "Health, Diseases & Symptoms",
    "subCategory": "Health, Diseases & Symptoms"
  },
  {
    "word": "Strain",
    "meaning": "A stretching or tearing of a muscle or a tissue connecting muscle to bone.",
    "pronunciation": "",
    "definition": "A stretching or tearing of a muscle or a tissue connecting muscle to bone.",
    "example": "",
    "category": "Health, Diseases & Symptoms",
    "subCategory": "Health, Diseases & Symptoms"
  },
  {
    "word": "Stroke",
    "meaning": "A medical emergency where blood flow to a part of the brain is interrupted or reduced.",
    "pronunciation": "",
    "definition": "A sudden disabling attack or loss of consciousness caused by an interruption in the flow of blood to the brain.",
    "example": "He experienced weakness on one side of his body, which is a common warning sign of a stroke.",
    "category": "Health, Diseases & Symptoms",
    "subCategory": "Health, Diseases & Symptoms"
  },
  {
    "word": "Sunburn",
    "meaning": "Inflammation of the skin caused by overexposure to ultraviolet radiation from the sun.",
    "pronunciation": "",
    "definition": "Inflammation of the skin caused by overexposure to ultraviolet radiation from the sun.",
    "example": "",
    "category": "Health, Diseases & Symptoms",
    "subCategory": "Health, Diseases & Symptoms"
  },
  {
    "word": "Suture",
    "meaning": "A stitch or row of stitches holding together the edges of a wound or surgical cut.",
    "pronunciation": "",
    "definition": "A stitch or row of stitches holding together the edges of a wound or surgical cut.",
    "example": "The surgeon applied sutures to the deep cut to ensure proper healing.",
    "category": "Health, Diseases & Symptoms",
    "subCategory": "Health, Diseases & Symptoms"
  },
  {
    "word": "Sweating",
    "meaning": "Exuding sweat as a result of being too hot, ill, or afraid.",
    "pronunciation": "",
    "definition": "Exuding sweat as a result of being too hot, ill, or afraid.",
    "example": "",
    "category": "Health, Diseases & Symptoms",
    "subCategory": "Health, Diseases & Symptoms"
  },
  {
    "word": "Swelling",
    "meaning": "An abnormal enlargement of a part of the body, typically as a result of an accumulation of fluid.",
    "pronunciation": "",
    "definition": "An abnormal enlargement of a part of the body, typically as a result of an accumulation of fluid.",
    "example": "",
    "category": "Health, Diseases & Symptoms",
    "subCategory": "Health, Diseases & Symptoms"
  },
  {
    "word": "Syphilis",
    "meaning": "A chronic bacterial disease that is contracted chiefly by infection during sexual intercourse.",
    "pronunciation": "",
    "definition": "A chronic bacterial disease that is contracted chiefly by infection during sexual intercourse.",
    "example": "",
    "category": "Health, Diseases & Symptoms",
    "subCategory": "Health, Diseases & Symptoms"
  },
  {
    "word": "Tetanus",
    "meaning": "A bacterial disease marked by rigidity and spasms of the voluntary muscles.",
    "pronunciation": "",
    "definition": "A bacterial disease marked by rigidity and spasms of the voluntary muscles.",
    "example": "",
    "category": "Health, Diseases & Symptoms",
    "subCategory": "Health, Diseases & Symptoms"
  },
  {
    "word": "Tingling",
    "meaning": "Experience or cause to experience a slight prickling or stinging sensation.",
    "pronunciation": "",
    "definition": "Experience or cause to experience a slight prickling or stinging sensation.",
    "example": "",
    "category": "Health, Diseases & Symptoms",
    "subCategory": "Health, Diseases & Symptoms"
  },
  {
    "word": "Tinnitus",
    "meaning": "Ringing or buzzing in the ears.",
    "pronunciation": "",
    "definition": "Ringing or buzzing in the ears.",
    "example": "",
    "category": "Health, Diseases & Symptoms",
    "subCategory": "Health, Diseases & Symptoms"
  },
  {
    "word": "Toothache",
    "meaning": "Pain in or around a tooth.",
    "pronunciation": "",
    "definition": "Pain in or around a tooth.",
    "example": "",
    "category": "Health, Diseases & Symptoms",
    "subCategory": "Health, Diseases & Symptoms"
  },
  {
    "word": "Tourniquet",
    "meaning": "A tight band tied around an arm or leg to stop severe bleeding.",
    "pronunciation": "",
    "definition": "A tight band tied around an arm or leg to stop severe bleeding.",
    "example": "The soldier used a tourniquet to stop the heavy bleeding from his leg wound.",
    "category": "Health, Diseases & Symptoms",
    "subCategory": "Health, Diseases & Symptoms"
  },
  {
    "word": "Trauma",
    "meaning": "A deeply distressing or disturbing experience, or a physical injury caused by an external force.",
    "pronunciation": "",
    "definition": "A deeply distressing or disturbing experience, or a physical injury caused by an external force.",
    "example": "The hospital has a specialized trauma center to treat patients with severe injuries.",
    "category": "Health, Diseases & Symptoms",
    "subCategory": "Health, Diseases & Symptoms"
  },
  {
    "word": "Tuberculosis",
    "meaning": "An infectious bacterial disease characterized by the growth of nodules in the tissues, especially the lungs.",
    "pronunciation": "",
    "definition": "An infectious bacterial disease characterized by the growth of nodules in the tissues, especially the lungs.",
    "example": "",
    "category": "Health, Diseases & Symptoms",
    "subCategory": "Health, Diseases & Symptoms"
  },
  {
    "word": "Typhoid",
    "meaning": "An infectious bacterial fever with an eruption of red spots on the chest and abdomen.",
    "pronunciation": "",
    "definition": "An infectious bacterial fever with an eruption of red spots on the chest and abdomen.",
    "example": "",
    "category": "Health, Diseases & Symptoms",
    "subCategory": "Health, Diseases & Symptoms"
  },
  {
    "word": "Ulcer",
    "meaning": "An open sore on an external or internal surface of the body, caused by a break in the skin or mucous membrane.",
    "pronunciation": "",
    "definition": "An open sore on an external or internal surface of the body, caused by a break in the skin or mucous membrane.",
    "example": "",
    "category": "Health, Diseases & Symptoms",
    "subCategory": "Health, Diseases & Symptoms"
  },
  {
    "word": "Unconscious",
    "meaning": "Lying in a state like sleep, completely unaware of your surroundings and unable to respond.",
    "pronunciation": "",
    "definition": "Lying in a state like sleep, completely unaware of your surroundings and unable to respond.",
    "example": "The driver was unconscious after the car accident, so we called for an ambulance immediately.",
    "category": "Health, Diseases & Symptoms",
    "subCategory": "Health, Diseases & Symptoms"
  },
  {
    "word": "Vertigo",
    "meaning": "A sensation of whirling and loss of balance.",
    "pronunciation": "",
    "definition": "A sensation of whirling and loss of balance.",
    "example": "",
    "category": "Health, Diseases & Symptoms",
    "subCategory": "Health, Diseases & Symptoms"
  },
  {
    "word": "Vomiting",
    "meaning": "Eject matter from the stomach through the mouth.",
    "pronunciation": "",
    "definition": "Eject matter from the stomach through the mouth.",
    "example": "",
    "category": "Health, Diseases & Symptoms",
    "subCategory": "Health, Diseases & Symptoms"
  },
  {
    "word": "Wheezing",
    "meaning": "Breathing with a whistling or rattling sound in the chest.",
    "pronunciation": "",
    "definition": "Breathing with a whistling or rattling sound in the chest.",
    "example": "",
    "category": "Health, Diseases & Symptoms",
    "subCategory": "Health, Diseases & Symptoms"
  },
  {
    "word": "Whiplash",
    "meaning": "Injury caused by a severe jerk to the head, typically in a motor-vehicle accident.",
    "pronunciation": "",
    "definition": "Injury caused by a severe jerk to the head, typically in a motor-vehicle accident.",
    "example": "",
    "category": "Health, Diseases & Symptoms",
    "subCategory": "Health, Diseases & Symptoms"
  },
  {
    "word": "Wound",
    "meaning": "घाव",
    "pronunciation": "/wu?nd/",
    "definition": "",
    "example": "",
    "category": "Health, Diseases & Symptoms",
    "subCategory": "Health, Diseases & Symptoms"
  }
]